qpoint/qpoint_class.py
qpoint/_version.py
qpoint/tools.py
qpoint/__init__.py
qpoint/qmap_class.py
qpoint/_libqpoint.py
qpoint/libqpoint.cpython-314t-darwin.so
qpoint-1.13.0.dist-info/RECORD
qpoint-1.13.0.dist-info/WHEEL
qpoint-1.13.0.dist-info/top_level.txt
qpoint-1.13.0.dist-info/METADATA
qpoint-1.13.0.dist-info/licenses/LICENSE
