Metadata-Version: 2.1
Name: qpoint
Version: 1.13.0
Summary: A lightweight quaternion-based library for efficient telescope pointing
Author-email: Alexandra Rahlin <arahlin@users.noreply.github.com>
License: MIT License
Project-URL: source, https://github.com/arahlin/qpoint
Requires-Python: >=3.8
License-File: LICENSE
Requires-Dist: numpy >1.10.0
Requires-Dist: scipy
Requires-Dist: astropy
